setup.cfg
setup.py
kmltrack/__init__.py
kmltrack/cli.py
kmltrack/fileconverter.py
kmltrack/generator.py
kmltrack/iterators.py
kmltrack/template.py
kmltrack/template_strings.py
kmltrack.egg-info/PKG-INFO
kmltrack.egg-info/SOURCES.txt
kmltrack.egg-info/dependency_links.txt
kmltrack.egg-info/entry_points.txt
kmltrack.egg-info/requires.txt
kmltrack.egg-info/top_level.txt