Metadata-Version: 1.0
Name: kmltrack
Version: 0.0.6
Summary: kmltrack converts a track (a series of lat/lon/timestamp and optional measurement values) into a kml file.
Home-page: https://github.com/SkyTruth/kmltrack
Author: Egil Moeller
Author-email: egil@skytruth.org
License: GPL
Keywords: kml
Platform: UNKNOWN
